amsterdam_schema/__init__.py
amsterdam_schema/types.py
amsterdam_schema/utils.py
amsterdam_schema-0.1.2.dist-info/METADATA
amsterdam_schema-0.1.2.dist-info/WHEEL
amsterdam_schema-0.1.2.dist-info/top_level.txt
amsterdam_schema-0.1.2.dist-info/RECORD
