Metadata-Version: 2.1
Name: amsterdam-schema
Version: 0.1.2
Summary: Python types for working with Amsterdam Schema
Home-page: https://github.com/Amsterdam/amsterdam-schema
Author: Jan Murre
Author-email: jan.murre@catalyz.nl
License: Mozilla Public 2.0
Platform: UNKNOWN
Classifier: Development Status :: 2 - Pre-Alpha
Classifier: License :: OSI Approved :: Mozilla Public License 2.0 (MPL 2.0)
Classifier: Programming Language :: Python
Classifier: Programming Language :: Python :: 3.7
Classifier: Programming Language :: Python :: 3.8
Requires-Dist: requests
Requires-Dist: jsonschema
Provides-Extra: tests
Requires-Dist: pytest ; extra == 'tests'
